telonex/__init__.py
telonex/_version.py
telonex/availability.py
telonex/constants.py
telonex/dataframe.py
telonex/download.py
telonex/exceptions.py
telonex/models.py
telonex-0.1.3.dist-info/METADATA
telonex-0.1.3.dist-info/WHEEL
telonex-0.1.3.dist-info/licenses/LICENSE
telonex-0.1.3.dist-info/RECORD
