Metadata-Version: 2.4
Name: telonex
Version: 0.1.3
Summary: Python client for Telonex prediction market data API
Project-URL: Homepage, https://telonex.io
Project-URL: Documentation, https://docs.telonex.io/python-sdk
Project-URL: Repository, https://github.com/ModestasGujis/telonex-python
Project-URL: Issues, https://github.com/ModestasGujis/telonex-python/issues
Author: Modestas
License-Expression: MIT
License-File: LICENSE
Classifier: Development Status :: 4 - Beta
Classifier: Intended Audience :: Developers
Classifier: Intended Audience :: Financial and Insurance Industry
Classifier: License :: OSI Approved :: MIT License
Classifier: Programming Language :: Python :: 3
Classifier: Programming Language :: Python :: 3.9
Classifier: Programming Language :: Python :: 3.10
Classifier: Programming Language :: Python :: 3.11
Classifier: Programming Language :: Python :: 3.12
Classifier: Topic :: Office/Business :: Financial
Classifier: Typing :: Typed
Requires-Python: >=3.9
Requires-Dist: aiofiles>=23.0.0
Requires-Dist: httpx>=0.25.0
Requires-Dist: nest-asyncio>=1.5.0
Requires-Dist: python-dateutil>=2.8.0
Provides-Extra: all
Requires-Dist: pandas>=2.0.0; extra == 'all'
Requires-Dist: polars>=0.20.0; extra == 'all'
Requires-Dist: pyarrow>=14.0.0; extra == 'all'
Provides-Extra: dataframe
Requires-Dist: pandas>=2.0.0; extra == 'dataframe'
Requires-Dist: pyarrow>=14.0.0; extra == 'dataframe'
Provides-Extra: dev
Requires-Dist: mypy; extra == 'dev'
Requires-Dist: pytest-asyncio>=0.23; extra == 'dev'
Requires-Dist: pytest-cov; extra == 'dev'
Requires-Dist: pytest>=8.0; extra == 'dev'
Requires-Dist: ruff; extra == 'dev'
Provides-Extra: polars
Requires-Dist: polars>=0.20.0; extra == 'polars'
